shaner/__init__.py
shaner/core.py
shaner/factory.py
shaner/utils.py
shaner-1.0.1.dist-info/LICENSE
shaner-1.0.1.dist-info/METADATA
shaner-1.0.1.dist-info/WHEEL
shaner-1.0.1.dist-info/top_level.txt
shaner-1.0.1.dist-info/RECORD
